README.md
mininft.py
setup.py
mininft.egg-info/PKG-INFO
mininft.egg-info/SOURCES.txt
mininft.egg-info/dependency_links.txt
mininft.egg-info/entry_points.txt
mininft.egg-info/requires.txt
mininft.egg-info/top_level.txt