Metadata-Version: 2.1
Name: mininft
Version: 1.0.4
Summary: Mini nft transfer helper
Home-page: https://github.com/tenuki/mininft
Author: tenuki
Author-email: dave@endlesstruction.com.ar
License: UNKNOWN
Platform: UNKNOWN
